obed/__init__.py
obed/argparsers.py
obed/decors.py
obed/obed.py
obed/objwalk.py
obed/secrets.py
obed/utils.py
obed/yavault.py
obed/examples/example.cmd2
obed/examples/example.json
obed/examples/example.yml
obed/examples/example_with_vault.cmd2
obed-0.2.11.dist-info/METADATA
obed-0.2.11.dist-info/WHEEL
obed-0.2.11.dist-info/entry_points.txt
obed-0.2.11.dist-info/top_level.txt
obed-0.2.11.dist-info/RECORD
