Metadata-Version: 2.4
Name: obed
Version: 0.2.11
Summary: interactiv object edit
Author: terasik
Project-URL: Homepage, https://github.com/terasik/inter
Project-URL: Issues, https://github.com/terasik/inter
Classifier: Programming Language :: Python :: 3.8
Classifier: Programming Language :: Python :: 3.9
Classifier: Programming Language :: Python :: 3.10
Classifier: Programming Language :: Python :: 3.11
Classifier: License :: OSI Approved :: MIT License
Classifier: Operating System :: OS Independent
Requires-Python: >=3.8
Requires-Dist: cmd2
Requires-Dist: jmespath
Requires-Dist: ansible-vault
Requires-Dist: PyYAML
Requires-Dist: importlib_resources
